autodistill_owlv2/__init__.py
autodistill_owlv2/owlv2_model.py
autodistill_owlv2-0.1.1.dist-info/LICENSE
autodistill_owlv2-0.1.1.dist-info/METADATA
autodistill_owlv2-0.1.1.dist-info/WHEEL
autodistill_owlv2-0.1.1.dist-info/top_level.txt
autodistill_owlv2-0.1.1.dist-info/RECORD
